FireLaunching.py
firelaunching/__init__.py
firelaunching/favicon.ico
firelaunching/settings.py
firelaunching-0.2.data/data/favicon.ico
structure/BruceSkyMainFrame.py
structure/BruceSkyMainPanel.py
structure/BruceSkyTaskBarIcon.py
structure/__init__.py
utils/Launcher.py
utils/Utils.py
utils/__init__.py
utils/tcp_server_new.py
utils/udp_server.py
firelaunching-0.2.dist-info/AUTHORS
firelaunching-0.2.dist-info/LICENSE
firelaunching-0.2.dist-info/METADATA
firelaunching-0.2.dist-info/WHEEL
firelaunching-0.2.dist-info/entry_points.txt
firelaunching-0.2.dist-info/top_level.txt
firelaunching-0.2.dist-info/RECORD
