Metadata-Version: 2.1
Name: firelaunching
Version: 0.2
Summary: This is a service of send messages
Home-page: UNKNOWN
Author: Bruce Yu
Author-email: 991138518@qq.com
License: BSD
Keywords: ftp udp
Platform: UNKNOWN
Classifier: Operating System :: OS Independent
Classifier: Intended Audience :: Developers
Classifier: License :: OSI Approved :: BSD License
Classifier: Programming Language :: Python
Classifier: Programming Language :: Python :: Implementation
Classifier: Programming Language :: Python :: 2
Classifier: Programming Language :: Python :: 2.7
Classifier: Programming Language :: Python :: 3
Classifier: Programming Language :: Python :: 3.4
Classifier: Programming Language :: Python :: 3.5
Classifier: Programming Language :: Python :: 3.6
Classifier: Topic :: Software Development :: Libraries
Requires-Python: >=2.7, !=3.0.*, !=3.1.*, !=3.2.*, !=3.3.*
Requires-Dist: wxPython (>=4.0.3)
Requires-Dist: chardet (>=3.0.4)
